tfswitch/__init__.py
tfswitch/cli.py
tfswitch-0.0.0.dist-info/METADATA
tfswitch-0.0.0.dist-info/WHEEL
tfswitch-0.0.0.dist-info/entry_points.txt
tfswitch-0.0.0.dist-info/top_level.txt
tfswitch-0.0.0.dist-info/RECORD
